<?xml version="1.0"?>
<Data><Image TextDescription=""><Attachment Name="PreviewMarker" Application="LAS AF" IsPreviewImage="0"/><ImageDescription><Channels><ChannelDescription DataType="0" ChannelTag="0" Resolution="16" NameOfMeasuredQuantity="" Min="0.000000e+000" Max="6.553500e+004" Unit="" LUTName="Green" IsLUTInverted="0" BytesInc="0" BitInc="0"></ChannelDescription><ChannelDescription DataType="0" ChannelTag="0" Resolution="16" NameOfMeasuredQuantity="" Min="0.000000e+000" Max="6.553500e+004" Unit="" LUTName="Gray" IsLUTInverted="0" BytesInc="2097152" BitInc="0"></ChannelDescription><ChannelDescription DataType="0" ChannelTag="0" Resolution="16" NameOfMeasuredQuantity="" Min="0.000000e+000" Max="6.553500e+004" Unit="" LUTName="Red" IsLUTInverted="0" BytesInc="4194304" BitInc="0"></ChannelDescription></Channels><Dimensions><DimensionDescription DimID="1" NumberOfElements="1024" Origin="-5.182475e-007" Length="2.449963e-004" Unit="m" BitInc="0" BytesInc="2"></DimensionDescription><DimensionDescription DimID="2" NumberOfElements="1024" Origin="-5.182475e-007" Length="2.449963e-004" Unit="m" BitInc="0" BytesInc="2048"></DimensionDescription><DimensionDescription DimID="3" NumberOfElements="70" Origin="4.070778e-003" Length="1.989788e-005" Unit="m" BitInc="0" BytesInc="6291456"></DimensionDescription></Dimensions></ImageDescription><TimeStampList NumberOfTimeStamps="210">1d9f7e3fe1de830 1d9f7e3fe1de830 1d9f7e4006b5aa0 1d9f7e402b91b30 1d9f7e402b91b30 1d9f7e40501d2b0 1d9f7e407518f10 1d9f7e407518f10 1d9f7e40999aa50 1d9f7e40bea7820 1d9f7e40bea7820 1d9f7e40e3f1680 1d9f7e41091b910 1d9f7e41091b910 1d9f7e412dae5c0 1d9f7e4152969a0 1d9f7e4152969a0 1d9f7e4177359a0 1d9f7e419c2a0d0 1d9f7e419c2a0d0 1d9f7e41c0c90d0 1d9f7e41e5a5160 1d9f7e41e5a5160 1d9f7e420a1a950 1d9f7e422f02d30 1d9f7e422f02d30 1d9f7e425389690 1d9f7e4278593d0 1d9f7e4278593d0 1d9f7e429ce4b50 1d9f7e42c1bbdc0 1d9f7e42c1bbdc0 1d9f7e42e6363d0 1d9f7e430ba4c20 1d9f7e430ba4c20 1d9f7e433054d90 1d9f7e43556deb0 1d9f7e43556deb0 1d9f7e437a5d7c0 1d9f7e439f2d500 1d9f7e439f2d500 1d9f7e43c3ac930 1d9f7e43e8a8590 1d9f7e43e8a8590 1d9f7e440d33d10 1d9f7e443248010 1d9f7e443248010 1d9f7e445717d50 1d9f7e447c29940 1d9f7e447c29940 1d9f7e44a0b02a0 1d9f7e44c57b1c0 1d9f7e44c57b1c0 1d9f7e44ea2b330 1d9f7e450f0e8f0 1d9f7e450f0e8f0 1d9f7e4533ad8f0 1d9f7e45589aaf0 1d9f7e45589aaf0 1d9f7e457d65a10 1d9f7e45a26b2b0 1d9f7e45a26b2b0 1d9f7e45c6ecdf0 1d9f7e45ebc1950 1d9f7e45ebc1950 1d9f7e46109d9e0 1d9f7e463580fa0 1d9f7e463580fa0 1d9f7e465a0c720 1d9f7e467ef4b00 1d9f7e467ef4b00 1d9f7e46a3e4410 1d9f7e46c8dd960 1d9f7e46c8dd960 1d9f7e46edad6a0 1d9f7e4712c67c0 1d9f7e4712c67c0 1d9f7e47376ccf0 1d9f7e475c4dba0 1d9f7e475c4dba0 1d9f7e4780e0850 1d9f7e47a673a90 1d9f7e47a673a90 1d9f7e47cb12a90 1d9f7e47efdd9b0 1d9f7e47efdd9b0 1d9f7e481469130 1d9f7e48397d430 1d9f7e48397d430 1d9f7e485dfc860 1d9f7e4882d88f0 1d9f7e4882d88f0 1d9f7e48a7778f0 1d9f7e48cc53980 1d9f7e48cc53980 1d9f7e48f0d54c0 1d9f7e4915e2290 1d9f7e4915e2290 1d9f7e493a6da10 1d9f7e495f6e490 1d9f7e495f6e490 1d9f7e498493900 1d9f7e49a9d1410 1d9f7e49a9d1410 1d9f7e49cec0d20 1d9f7e49f3a9100 1d9f7e49f3a9100 1d9f7e4a1834880 1d9f7e4a3d48b80 1d9f7e4a3d48b80 1d9f7e4a61bbc60 1d9f7e4a8692ed0 1d9f7e4a8692ed0 1d9f7e4aab1e650 1d9f7e4ad02b420 1d9f7e4ad02b420 1d9f7e4af4ca420 1d9f7e4b19d23d0 1d9f7e4b19d23d0 1d9f7e4b3e51800 1d9f7e4b6334dc0 1d9f7e4b6334dc0 1d9f7e4b87c7a70 1d9f7e4bacd4840 1d9f7e4bacd4840 1d9f7e4bd1da0e0 1d9f7e4bf6b1350 1d9f7e4bf6b1350 1d9f7e4c1b37cb0 1d9f7e4c3ffb6a0 1d9f7e4c3ffb6a0 1d9f7e4c646e780 1d9f7e4c89878a0 1d9f7e4c89878a0 1d9f7e4cae21a80 1d9f7e4cd2f17c0 1d9f7e4cd2f17c0 1d9f7e4cf778120 1d9f7e4d1c91240 1d9f7e4d1c91240 1d9f7e4d4123ef0 1d9f7e4d65f8a50 1d9f7e4d65f8a50 1d9f7e4d8a9ef80 1d9f7e4daff9f50 1d9f7e4daff9f50 1d9f7e4dd4ee680 1d9f7e4df9d6a60 1d9f7e4df9d6a60 1d9f7e4e1e648f0 1d9f7e4e43764e0 1d9f7e4e43764e0 1d9f7e4e67f8020 1d9f7e4e8ce5220 1d9f7e4e8ce5220 1d9f7e4eb190570 1d9f7e4ed678950 1d9f7e4ed678950 1d9f7e4efb0b600 1d9f7e4f1feebc0 1d9f7e4f1feebc0 1d9f7e4f4481870 1d9f7e4f69b7e50 1d9f7e4f69b7e50 1d9f7e4f9032f80 1d9f7e4fb56bc70 1d9f7e4fb56bc70 1d9f7e4fd9eb0a0 1d9f7e4fff28bb0 1d9f7e4fff28bb0 1d9f7e502441cd0 1d9f7e50491dd60 1d9f7e50491dd60 1d9f7e506da46c0 1d9f7e509274400 1d9f7e509274400 1d9f7e50b74b670 1d9f7e50dc954d0 1d9f7e50dc954d0 1d9f7e510114900 1d9f7e5125fcce0 1d9f7e5125fcce0 1d9f7e514a79a00 1d9f7e516f66c00 1d9f7e516f66c00 1d9f7e519405c00 1d9f7e51b8edfe0 1d9f7e51b8edfe0 1d9f7e51dd8cfe0 1d9f7e5202d6e40 1d9f7e5202d6e40 1d9f7e522751450 1d9f7e524c59400 1d9f7e524c59400 1d9f7e5270f8400 1d9f7e5295c8140 1d9f7e5295c8140 1d9f7e52ba538c0 1d9f7e52df78d30 1d9f7e52df78d30 1d9f7e5304b1a20 1d9f7e532986580 1d9f7e532986580 1d9f7e534e14410 1d9f7e53735e270 1d9f7e53735e270 1d9f7e53982dfb0 1d9f7e53bcfdcf0 1d9f7e53bcfdcf0 1d9f7e53e1909a0 </TimeStampList><Attachment Name="ChannelAttachment" Application="LAS AF"/><Attachment Name="ViewerScaling" Application="LAS AF"><ChannelScalingInfo BackgroundLutName="" WhiteValue="1" BlackValue="0" GammaValue="1" Automatic="0"/><ChannelScalingInfo BackgroundLutName="" WhiteValue="1" BlackValue="0" GammaValue="1" Automatic="0"/><ChannelScalingInfo BackgroundLutName="" WhiteValue="1" BlackValue="0" GammaValue="1" Automatic="0"/></Attachment><Attachment Name="ImageXMLDocument" Application="LAS AF"><RootNode/>
		</Attachment><Attachment Name="HardwareSetting" Application="LAS AF" Software="LAS X 3.5.7.23225" HardwareServerVersion="Build 23225" SystemType="12" SystemTypeName="TCS SP8" DataSourceType="0" DataSourceTypeName="Confocal"><ATLConfocalSettingDefinition VersionNumber="15" UserSettingName="S44" CanDoSTED="0" IsSTEDActive="0" IsSwitchForPulsedStedWithMpActive="0" UseSystemOptimizedVoxelCalculation="1" IsUserSettingNameSet="0" IsHydPulsedModeCoeffntManualActive="0" XGalvoMovementMode="0" XGalvoMovementModeName="sinus" BitSize="16" MaxIntegrationTime="0" ScanMode="xyz" ZUseMode="2" ZUseModeName="z-wide" ZPosition="0.004090676275" IsSuperZ="0" ValidBeginStack="1" ValidEndStack="1" Begin="0.0040707784" End="0.004090676275" Sections="70" StackCalculationMode="1" StackCalculationModeName="Constant step size" IsMPFormulaForStepSizerUsageActive="0" IsFastZStack="0" ZStackDirectionMode="1" ZStackDirectionModeName="Unidirectional" Magnification="63" ObjectivePos="2" ObjectiveName="HC PL APO CS2    63x/1.40 OIL " ObjectiveNumber="11506350" MicroscopeModel="DMI8-CS" IsInverseMicroscopeModel="1" Immersion="OIL" NumericalAperture="1.4" RefractionIndex="1.518" IsFCSFilterAutomationActive="0" IsSMDChaserUVAOTFAutomationActive="0" CanDoCSMode="1" ActiveCS_SubModeForTLD="0" ActiveCS_SubModeForTLDName="Scan-BF" ActiveCS_SubModeForRLD="0" ActiveCS_SubModeForRLDName="Empty" RldFluoCubePos="3" RldCubeAutoSelectionEnabled="1" LastNonMP_MFP_FW_Name="" LastNonMP_Pol_FW_Name="" ScanSpeed="400" InDimension="1024" OutDimension="1024" UseScanFormatRestriction="0" Zoom="0.753169763724629" BaseZoom="0.75" PanFirstDim="-3.26495895630026E-05" PanSecondDim="-3.26495895630026E-05" ScanDirectionX="1" ScanDirectionXName="Unidirectional" Pinhole="9.62667674286794E-05" PinholeAiry="1.00775461579758" EmissionWavelengthForPinholeAiryCalculation="580" FrameAverage="1" LineAverage="1" FrameAccumulation="1" Line_Accumulation="1" AreBleachPointsEnabled="0" InTrigger="-1" OutTrigger="-1" IsRoiScanEnable="0" Is3DLimitedRoiScanEnable="0" ZCompensationModes="0" WizardMode="0" IsConstantIntegrationTimeActive="1" PixelDwellTime="0.0000006" SystemSerialNumber="8100001094"><EasySRMappingArray/><EasySRSlider SRRelative="75" ThreeDRelative="0" GentleRelative="25"/><Quantity Value="0.000000288375" Unit="m"/><AdditionalZPositionList><AdditionalZPosition Valid="1" SuperZMode="1" SuperZModeName="RestrictedRange" ZMode="2" ZUseModeName="z-wide" ZPosition="0.004090676275"/></AdditionalZPositionList><ShutterList><Shutter Version="0" LightSourceType="1" LightSourceName="UV" IsActive="0"><BeamRoute Version="0"><BeamPosition BeamPositionLevel="0" BeamPosition="30"/></BeamRoute></Shutter><Shutter Version="0" LightSourceType="0" LightSourceName="Visible" IsActive="1"><BeamRoute Version="0"><BeamPosition BeamPositionLevel="0" BeamPosition="10"/></BeamRoute></Shutter></ShutterList><BleachPoints><LMSDataContainerHeader Version="2"><Element Name="BleachPointROISet" Visibility="2" CopyOption="1" UniqueID="77353398-63d8-11ee-a640-001577e97467"><Data><ROISet ROISetType="1" PossibleChildROITypes="-1" PossibleROITransforms="65535" PossibleROIActions="65535"/></Data>
							<Memory Size="0" MemoryBlockID="MemBlock_5099"/><Children/></Element></LMSDataContainerHeader>
				</BleachPoints><ATLConfocalBleachPointsSettings/><FilterWheel FluorifierAutoSelection="1" BeamSplitterAutoSelection="1" StedBeamSelectionPinholeCoupling="0" MultiFunctionPortAutoSelection="0" BeamMergerAutoSelectionEnabled="0" RldBlockingFilterAutoSelectionEnabled="0"><Wheel Version="0" Qualifier="40" FilterWheelName="Excitation Beam Splitter" FilterIndex="2" FilterName="DD 488/552" IsSpectrumTurnMode="0" FilterSpectrumPos="0" IndexChanged="0" SpectrumChanged="0"><BeamRoute Version="0"/></Wheel><Wheel Version="0" Qualifier="131" FilterWheelName="Notch FW 2" FilterIndex="1" FilterName="NF 552" IsSpectrumTurnMode="0" FilterSpectrumPos="0" IndexChanged="0" SpectrumChanged="0"><BeamRoute Version="0"/></Wheel><Wheel Version="0" Qualifier="130" FilterWheelName="Polarization FW" FilterIndex="0" FilterName="Empty" IsSpectrumTurnMode="0" FilterSpectrumPos="79196" IndexChanged="0" SpectrumChanged="0"><BeamRoute Version="0"/></Wheel><Wheel Version="0" Qualifier="170" FilterWheelName="Target Slider" FilterIndex="0" FilterName="Target Park " IsSpectrumTurnMode="0" FilterSpectrumPos="0" IndexChanged="0" SpectrumChanged="0"><BeamRoute Version="0"/></Wheel><Wheel Version="0" Qualifier="31" FilterWheelName="X2 Lens Changer" FilterIndex="0" FilterName="CS2 UV Optics 1 " IsSpectrumTurnMode="0" FilterSpectrumPos="0" IndexChanged="0" SpectrumChanged="0"><BeamRoute Version="0"/></Wheel></FilterWheel><Spectro><MultiBand Channel="1" ChannelName="Channel 1" LeftWorld="493" RightWorld="557" TargetWaveLengthBegin="493" TargetWaveLengthEnd="557" DyeName=""/><MultiBand Channel="2" ChannelName="Channel 2" LeftWorld="557" RightWorld="789" TargetWaveLengthBegin="557" TargetWaveLengthEnd="789" DyeName="Leica/mCherry"/><MultiBand Channel="3" ChannelName="Channel 3" LeftWorld="790" RightWorld="795" TargetWaveLengthBegin="790" TargetWaveLengthEnd="795" DyeName=""/><MultiBand Channel="4" ChannelName="Channel 4" LeftWorld="795" RightWorld="800" TargetWaveLengthBegin="795" TargetWaveLengthEnd="800" DyeName=""/></Spectro><AotfList><Aotf Version="0" LightSourceName="UV" LightSourceType="1" OpenVirtual="0" IsChanged="0" CanDoPulseFreq="0" PulsFreq="0" CanDoTwoLaserPIE="0" TwoLaserPIEPossibleLastState="0" TwoLaserPIEActive="0"><BeamRoute Version="0"><BeamPosition BeamPositionLevel="0" BeamPosition="30"/></BeamRoute><LaserLineSetting LaserLine="405" IntensityDev="0" IntensityLowDev="0" AOBSIntensityDev="-1" AOBSIntensityLowDev="-1" EnableDoubleMode="0" LineIndex="0" SequenceIndex="0" LineDeactivationFlags="0" IsLineChecked="1" OutCheckedIntensity="0" SuppressionMode="-1" IsVisible="1" CanDoFastModulation="1"/></Aotf><Aotf Version="0" LightSourceName="Visible" LightSourceType="0" OpenVirtual="0" IsChanged="0" CanDoPulseFreq="0" PulsFreq="0" CanDoTwoLaserPIE="0" TwoLaserPIEPossibleLastState="0" TwoLaserPIEActive="0"><BeamRoute Version="0"><BeamPosition BeamPositionLevel="0" BeamPosition="10"/></BeamRoute><LaserLineSetting LaserLine="488" IntensityDev="0" IntensityLowDev="0" AOBSIntensityDev="-1" AOBSIntensityLowDev="-1" EnableDoubleMode="0" LineIndex="0" SequenceIndex="0" LineDeactivationFlags="0" IsLineChecked="1" OutCheckedIntensity="0" SuppressionMode="-1" IsVisible="1" CanDoFastModulation="1"/><LaserLineSetting LaserLine="552" IntensityDev="75.000000000006" IntensityLowDev="0" AOBSIntensityDev="-1" AOBSIntensityLowDev="-1" EnableDoubleMode="0" LineIndex="1" SequenceIndex="0" LineDeactivationFlags="0" IsLineChecked="1" OutCheckedIntensity="0" SuppressionMode="-1" IsVisible="1" CanDoFastModulation="1"/><LaserLineSetting LaserLine="638" IntensityDev="0" IntensityLowDev="0" AOBSIntensityDev="-1" AOBSIntensityLowDev="-1" EnableDoubleMode="0" LineIndex="2" SequenceIndex="0" LineDeactivationFlags="0" IsLineChecked="1" OutCheckedIntensity="0" SuppressionMode="-1" IsVisible="1" CanDoFastModulation="1"/></Aotf></AotfList><LUT_List><LUT Channel="1" LutName="Blue"/><LUT Channel="2" LutName="Red"/><LUT Channel="3" LutName="Red"/><LUT Channel="4" LutName="Blue"/><LUT Channel="100" LutName="Gray"/></LUT_List><DetectorList DetectorAutoSelection="1" InExternalDetectionMode="0"><Detector Name="PMT 1" Type="PMT" ScanType="Internal" Channel="1" ChannelName="Channel 1" IsActive="0" Gain="732.318608377203" Offset="0" IsSTEDDetector="1" IsSRSDetector="0" DetectionRangeBegin="0" DetectionRangeEnd="0" Phase="0" IsFlimDetector="0" IsHPDDetector="0" CanDoTimeGate="0"/><Detector Name="PMT 2" Type="PMT" ScanType="Internal" Channel="2" ChannelName="Channel 2" IsActive="1" Gain="658.350499732967" Offset="0" IsSTEDDetector="1" IsSRSDetector="0" DetectionRangeBegin="0" DetectionRangeEnd="0" Phase="0" IsFlimDetector="0" IsHPDDetector="0" CanDoTimeGate="0"/><Detector Name="HyD 3" Type="HyD" ScanType="Internal" Channel="3" ChannelName="Channel 3" IsActive="0" Gain="500" Offset="-6.6666666666606E-03" IsSTEDDetector="1" IsSRSDetector="0" DetectionRangeBegin="0" DetectionRangeEnd="0" Phase="0" IsFlimDetector="0" IsHPDDetector="1" IsEnabled="0" IsHPDOverloaded="0" CanDoPhotonCounting="1" AcquisitionMode="0" AcquisitionModeName="PhotonIntegration" CanDoTimeGate="0"/><Detector Name="HyD 4" Type="HyD" ScanType="Internal" Channel="4" ChannelName="Channel 4" IsActive="0" Gain="99.9981315396114" Offset="-6.6666666666606E-03" IsSTEDDetector="1" IsSRSDetector="0" DetectionRangeBegin="0" DetectionRangeEnd="0" Phase="0" IsFlimDetector="0" IsHPDDetector="1" IsEnabled="0" IsHPDOverloaded="0" CanDoPhotonCounting="1" AcquisitionMode="0" AcquisitionModeName="PhotonIntegration" CanDoTimeGate="0"/><Detector Name="PMT Trans" Type="PMT" ScanType="TLD" Channel="100" ChannelName="Transmission Channel" IsActive="0" Gain="190.165560387579" Offset="0" IsSTEDDetector="0" IsSRSDetector="0" DetectionRangeBegin="0" DetectionRangeEnd="0" Phase="0" IsFlimDetector="0" IsHPDDetector="0" CanDoTimeGate="0"/></DetectorList><LaserArray><Laser Version="6" LightSourceType="1" LaserName="Diode 405" PowerState="Off" StedAlignFlag="0" CanDoLinearOutputPower="0" CanDoPulsing="0" CanDoOutputPowerWatt="1" HighPowerModeActive="0" LightSourceName="UV" OutputPowerWatt="0" Wavelength="405" CanDoChangeWavelength="0"><BeamRoute Version="0"><BeamPosition BeamPositionLevel="0" BeamPosition="30"/></BeamRoute></Laser><Laser Version="6" LightSourceType="0" LaserName="Diode 638" PowerState="Off" StedAlignFlag="0" CanDoLinearOutputPower="0" CanDoPulsing="0" CanDoOutputPowerWatt="1" HighPowerModeActive="0" LightSourceName="Visible" OutputPowerWatt="0" Wavelength="638" CanDoChangeWavelength="0"><BeamRoute Version="0"><BeamPosition BeamPositionLevel="0" BeamPosition="10"/></BeamRoute></Laser><Laser Version="6" LightSourceType="0" LaserName="OPSL 488" PowerState="On" StedAlignFlag="0" CanDoLinearOutputPower="0" CanDoPulsing="0" CanDoOutputPowerWatt="1" HighPowerModeActive="0" LightSourceName="Visible" OutputPowerWatt="0" Wavelength="488" CanDoChangeWavelength="0"><BeamRoute Version="0"><BeamPosition BeamPositionLevel="0" BeamPosition="10"/></BeamRoute></Laser><Laser Version="6" LightSourceType="0" LaserName="OPSL 552" PowerState="On" StedAlignFlag="0" CanDoLinearOutputPower="0" CanDoPulsing="0" CanDoOutputPowerWatt="1" HighPowerModeActive="0" LightSourceName="Visible" OutputPowerWatt="0" Wavelength="552" CanDoChangeWavelength="0"><BeamRoute Version="0"><BeamPosition BeamPositionLevel="0" BeamPosition="10"/></BeamRoute></Laser></LaserArray><OnlineDyeSeparation Enabled="0" KeepRawImage="0" Detectors="0" Channels="0" Normalize="0"><OnlineDyeSeparationDetectorList/><OnlineDyeSeparationChannelList/></OnlineDyeSeparation><VariableBeamExpanderFactors CommonSettingEnabled="0" CommonFactor="1.03"/></ATLConfocalSettingDefinition><LDM_Block_Sequential SequentialMode="1" AutoFocusSequence="1" BlockName="Job(Seq.Scan) 1"><LDM_Block_Sequential_Master><ATLConfocalSettingDefinition VersionNumber="15" UserSettingName="S8" CanDoSTED="0" IsSTEDActive="0" IsSwitchForPulsedStedWithMpActive="0" UseSystemOptimizedVoxelCalculation="1" IsUserSettingNameSet="0" IsHydPulsedModeCoeffntManualActive="0" XGalvoMovementMode="0" XGalvoMovementModeName="sinus" BitSize="16" MaxIntegrationTime="0" ScanMode="xyz" ZUseMode="2" ZUseModeName="z-wide" ZPosition="0.0040906955" IsSuperZ="0" ValidBeginStack="1" ValidEndStack="1" Begin="0.0040707784" End="0.004090676275" Sections="70" StackCalculationMode="1" StackCalculationModeName="Constant step size" IsMPFormulaForStepSizerUsageActive="0" IsFastZStack="0" ZStackDirectionMode="1" ZStackDirectionModeName="Unidirectional" Magnification="63" ObjectivePos="2" ObjectiveName="HC PL APO CS2    63x/1.40 OIL " ObjectiveNumber="11506350" MicroscopeModel="DMI8-CS" IsInverseMicroscopeModel="1" Immersion="OIL" NumericalAperture="1.4" RefractionIndex="1.518" IsFCSFilterAutomationActive="0" IsSMDChaserUVAOTFAutomationActive="0" CanDoCSMode="1" ActiveCS_SubModeForTLD="0" ActiveCS_SubModeForTLDName="Scan-BF" RldFluoCubePos="3" RldCubeAutoSelectionEnabled="1" LastNonMP_MFP_FW_Name="" LastNonMP_Pol_FW_Name="" ScanSpeed="400" InDimension="1024" OutDimension="1024" UseScanFormatRestriction="0" Zoom="0.753169763724629" BaseZoom="0.75" PanFirstDim="-1.34901747844103E-03" PanSecondDim="-6.60937079042799E-04" ScanDirectionX="1" ScanDirectionXName="Unidirectional" Pinhole="9.55071217291706E-05" PinholeAiry="0.999802375574928" EmissionWavelengthForPinholeAiryCalculation="580" FrameAverage="1" LineAverage="1" FrameAccumulation="1" Line_Accumulation="1" AreBleachPointsEnabled="0" InTrigger="-1" OutTrigger="-1" IsRoiScanEnable="0" Is3DLimitedRoiScanEnable="0" ZCompensationModes="0" WizardMode="0" IsConstantIntegrationTimeActive="1" PixelDwellTime="0.0000006" SystemSerialNumber="8100001094"><EasySRMappingArray/><EasySRSlider SRRelative="75" ThreeDRelative="0" GentleRelative="25"/><Quantity Value="0.000000288375" Unit="m"/><AdditionalZPositionList><AdditionalZPosition Valid="1" SuperZMode="1" SuperZModeName="RestrictedRange" ZMode="2" ZUseModeName="z-wide" ZPosition="0.0040906955"/></AdditionalZPositionList><ShutterList><Shutter Version="0" LightSourceType="1" LightSourceName="UV" IsActive="0"><BeamRoute Version="0"><BeamPosition BeamPositionLevel="0" BeamPosition="30"/></BeamRoute></Shutter><Shutter Version="0" LightSourceType="0" LightSourceName="Visible" IsActive="1"><BeamRoute Version="0"><BeamPosition BeamPositionLevel="0" BeamPosition="10"/></BeamRoute></Shutter></ShutterList><BleachPoints><LMSDataContainerHeader Version="2"><Element Name="BleachPointROISet" Visibility="2" CopyOption="1" UniqueID="e037f09e-63ce-11ee-a640-001577e97467"><Data><ROISet ROISetType="1" PossibleChildROITypes="-1" PossibleROITransforms="65535" PossibleROIActions="65535"/></Data>
									<Memory Size="0" MemoryBlockID="MemBlock_3808"/><Children/></Element></LMSDataContainerHeader>
						</BleachPoints><ATLConfocalBleachPointsSettings/><FilterWheel FluorifierAutoSelection="1" BeamSplitterAutoSelection="1" StedBeamSelectionPinholeCoupling="0" MultiFunctionPortAutoSelection="0" BeamMergerAutoSelectionEnabled="0" RldBlockingFilterAutoSelectionEnabled="0"><Wheel Version="0" Qualifier="40" FilterWheelName="Excitation Beam Splitter" FilterIndex="2" FilterName="DD 488/552" IsSpectrumTurnMode="0" FilterSpectrumPos="0" IndexChanged="0" SpectrumChanged="0"><BeamRoute Version="0"/></Wheel><Wheel Version="0" Qualifier="131" FilterWheelName="Notch FW 2" FilterIndex="1" FilterName="NF 552" IsSpectrumTurnMode="0" FilterSpectrumPos="0" IndexChanged="1" SpectrumChanged="0"><BeamRoute Version="0"/></Wheel><Wheel Version="0" Qualifier="130" FilterWheelName="Polarization FW" FilterIndex="0" FilterName="Empty" IsSpectrumTurnMode="0" FilterSpectrumPos="79196" IndexChanged="1" SpectrumChanged="0"><BeamRoute Version="0"/></Wheel><Wheel Version="0" Qualifier="170" FilterWheelName="Target Slider" FilterIndex="0" FilterName="Target Park " IsSpectrumTurnMode="0" FilterSpectrumPos="0" IndexChanged="0" SpectrumChanged="0"><BeamRoute Version="0"/></Wheel><Wheel Version="0" Qualifier="31" FilterWheelName="X2 Lens Changer" FilterIndex="0" FilterName="CS2 UV Optics 1 " IsSpectrumTurnMode="0" FilterSpectrumPos="0" IndexChanged="0" SpectrumChanged="0"><BeamRoute Version="0"/></Wheel></FilterWheel><Spectro><MultiBand Channel="1" ChannelName="Channel 1" LeftWorld="493" RightWorld="659" TargetWaveLengthBegin="493" TargetWaveLengthEnd="659" DyeName=""/><MultiBand Channel="2" ChannelName="Channel 2" LeftWorld="659" RightWorld="789" TargetWaveLengthBegin="659" TargetWaveLengthEnd="789" DyeName=""/><MultiBand Channel="3" ChannelName="Channel 3" LeftWorld="790" RightWorld="795" TargetWaveLengthBegin="790" TargetWaveLengthEnd="795" DyeName=""/><MultiBand Channel="4" ChannelName="Channel 4" LeftWorld="795" RightWorld="800" TargetWaveLengthBegin="795" TargetWaveLengthEnd="800" DyeName=""/></Spectro><AotfList><Aotf Version="0" LightSourceName="UV" LightSourceType="1" OpenVirtual="0" IsChanged="0" CanDoPulseFreq="0" PulsFreq="0" CanDoTwoLaserPIE="0" TwoLaserPIEPossibleLastState="0" TwoLaserPIEActive="0"><BeamRoute Version="0"><BeamPosition BeamPositionLevel="0" BeamPosition="30"/></BeamRoute><LaserLineSetting LaserLine="405" IntensityDev="0" IntensityLowDev="0" AOBSIntensityDev="-1" AOBSIntensityLowDev="-1" EnableDoubleMode="0" LineIndex="0" SequenceIndex="0" LineDeactivationFlags="0" IsLineChecked="1" OutCheckedIntensity="0" SuppressionMode="-1" IsVisible="1" CanDoFastModulation="1"/></Aotf><Aotf Version="0" LightSourceName="Visible" LightSourceType="0" OpenVirtual="0" IsChanged="1" CanDoPulseFreq="0" PulsFreq="0" CanDoTwoLaserPIE="0" TwoLaserPIEPossibleLastState="0" TwoLaserPIEActive="0"><BeamRoute Version="0"><BeamPosition BeamPositionLevel="0" BeamPosition="10"/></BeamRoute><LaserLineSetting LaserLine="488" IntensityDev="75.000000000006" IntensityLowDev="0" AOBSIntensityDev="-1" AOBSIntensityLowDev="-1" EnableDoubleMode="0" LineIndex="0" SequenceIndex="0" LineDeactivationFlags="0" IsLineChecked="1" OutCheckedIntensity="0" SuppressionMode="-1" IsVisible="1" CanDoFastModulation="1"/><LaserLineSetting LaserLine="552" IntensityDev="49.9952060174489" IntensityLowDev="0" AOBSIntensityDev="-1" AOBSIntensityLowDev="-1" EnableDoubleMode="0" LineIndex="1" SequenceIndex="0" LineDeactivationFlags="0" IsLineChecked="1" OutCheckedIntensity="0" SuppressionMode="-1" IsVisible="1" CanDoFastModulation="1"/><LaserLineSetting LaserLine="638" IntensityDev="0" IntensityLowDev="0" AOBSIntensityDev="-1" AOBSIntensityLowDev="-1" EnableDoubleMode="0" LineIndex="2" SequenceIndex="0" LineDeactivationFlags="0" IsLineChecked="1" OutCheckedIntensity="0" SuppressionMode="-1" IsVisible="1" CanDoFastModulation="1"/></Aotf></AotfList><LUT_List><LUT Channel="1" LutName="Blue"/><LUT Channel="2" LutName="Red"/><LUT Channel="3" LutName="Red"/><LUT Channel="4" LutName="Blue"/><LUT Channel="100" LutName="Gray"/></LUT_List><DetectorList DetectorAutoSelection="1" InExternalDetectionMode="0"><Detector Name="PMT 1" Type="PMT" ScanType="Internal" Channel="1" ChannelName="Channel 1" IsActive="0" Gain="732.318608377203" Offset="0" IsSTEDDetector="1" IsSRSDetector="0" DetectionRangeBegin="0" DetectionRangeEnd="0" Phase="0" IsFlimDetector="0" IsHPDDetector="0" CanDoTimeGate="0"/><Detector Name="PMT 2" Type="PMT" ScanType="Internal" Channel="2" ChannelName="Channel 2" IsActive="1" Gain="658.350499732967" Offset="0" IsSTEDDetector="1" IsSRSDetector="0" DetectionRangeBegin="0" DetectionRangeEnd="0" Phase="0" IsFlimDetector="0" IsHPDDetector="0" CanDoTimeGate="0"/><Detector Name="HyD 3" Type="HyD" ScanType="Internal" Channel="3" ChannelName="Channel 3" IsActive="0" Gain="500" Offset="-6.6666666666606E-03" IsSTEDDetector="1" IsSRSDetector="0" DetectionRangeBegin="0" DetectionRangeEnd="0" Phase="0" IsFlimDetector="0" IsHPDDetector="1" IsEnabled="0" IsHPDOverloaded="0" CanDoPhotonCounting="1" AcquisitionMode="0" AcquisitionModeName="PhotonIntegration" CanDoTimeGate="0"/><Detector Name="HyD 4" Type="HyD" ScanType="Internal" Channel="4" ChannelName="Channel 4" IsActive="0" Gain="99.9981315396114" Offset="-6.6666666666606E-03" IsSTEDDetector="1" IsSRSDetector="0" DetectionRangeBegin="0" DetectionRangeEnd="0" Phase="0" IsFlimDetector="0" IsHPDDetector="1" IsEnabled="0" IsHPDOverloaded="0" CanDoPhotonCounting="1" AcquisitionMode="0" AcquisitionModeName="PhotonIntegration" CanDoTimeGate="0"/><Detector Name="PMT Trans" Type="PMT" ScanType="TLD" Channel="100" ChannelName="Transmission Channel" IsActive="1" Gain="190.165560387579" Offset="0" IsSTEDDetector="0" IsSRSDetector="0" DetectionRangeBegin="0" DetectionRangeEnd="0" Phase="0" IsFlimDetector="0" IsHPDDetector="0" CanDoTimeGate="0"/></DetectorList><LaserArray><Laser Version="6" LightSourceType="1" LaserName="Diode 405" PowerState="Off" StedAlignFlag="0" CanDoLinearOutputPower="0" CanDoPulsing="0" CanDoOutputPowerWatt="1" HighPowerModeActive="0" LightSourceName="UV" OutputPowerWatt="0" Wavelength="405" CanDoChangeWavelength="0"><BeamRoute Version="0"><BeamPosition BeamPositionLevel="0" BeamPosition="30"/></BeamRoute></Laser><Laser Version="6" LightSourceType="0" LaserName="Diode 638" PowerState="Off" StedAlignFlag="0" CanDoLinearOutputPower="0" CanDoPulsing="0" CanDoOutputPowerWatt="1" HighPowerModeActive="0" LightSourceName="Visible" OutputPowerWatt="0" Wavelength="638" CanDoChangeWavelength="0"><BeamRoute Version="0"><BeamPosition BeamPositionLevel="0" BeamPosition="10"/></BeamRoute></Laser><Laser Version="6" LightSourceType="0" LaserName="OPSL 488" PowerState="On" StedAlignFlag="0" CanDoLinearOutputPower="0" CanDoPulsing="0" CanDoOutputPowerWatt="1" HighPowerModeActive="0" LightSourceName="Visible" OutputPowerWatt="0" Wavelength="488" CanDoChangeWavelength="0"><BeamRoute Version="0"><BeamPosition BeamPositionLevel="0" BeamPosition="10"/></BeamRoute></Laser><Laser Version="6" LightSourceType="0" LaserName="OPSL 552" PowerState="On" StedAlignFlag="0" CanDoLinearOutputPower="0" CanDoPulsing="0" CanDoOutputPowerWatt="1" HighPowerModeActive="0" LightSourceName="Visible" OutputPowerWatt="0" Wavelength="552" CanDoChangeWavelength="0"><BeamRoute Version="0"><BeamPosition BeamPositionLevel="0" BeamPosition="10"/></BeamRoute></Laser></LaserArray><OnlineDyeSeparation Enabled="0" KeepRawImage="0" Detectors="0" Channels="0" Normalize="0"><OnlineDyeSeparationDetectorList/><OnlineDyeSeparationChannelList/></OnlineDyeSeparation><VariableBeamExpanderFactors CommonSettingEnabled="0" CommonFactor="1.03"/></ATLConfocalSettingDefinition></LDM_Block_Sequential_Master><LDM_Block_Sequential_List><ATLConfocalSettingDefinition VersionNumber="15" UserSettingName="Seq. 1" CanDoSTED="0" IsSTEDActive="0" IsSwitchForPulsedStedWithMpActive="0" UseSystemOptimizedVoxelCalculation="1" IsUserSettingNameSet="1" IsHydPulsedModeCoeffntManualActive="0" CanDoCSMode="1" ActiveCS_SubModeForTLD="0" ActiveCS_SubModeForTLDName="Scan-BF" ActiveCS_SubModeForRLD="0" ActiveCS_SubModeForRLDName="Empty" RldFluoCubePos="-1" RldCubeAutoSelectionEnabled="1" Pinhole="9.55071217291706E-05" PinholeAiry="0.999802375574928" EmissionWavelengthForPinholeAiryCalculation="580" FrameAverage="1" LineAverage="1" FrameAccumulation="1" Line_Accumulation="1" AreBleachPointsEnabled="0" IsRoiScanEnable="0" ZCompensationModes="0" WizardMode="0"><EasySRMappingArray/><EasySRSlider SRRelative="75" ThreeDRelative="0" GentleRelative="25"/><ShutterList><Shutter Version="0" LightSourceType="1" LightSourceName="UV" IsActive="0"><BeamRoute Version="0"><BeamPosition BeamPositionLevel="0" BeamPosition="30"/></BeamRoute></Shutter><Shutter Version="0" LightSourceType="0" LightSourceName="Visible" IsActive="1"><BeamRoute Version="0"><BeamPosition BeamPositionLevel="0" BeamPosition="10"/></BeamRoute></Shutter></ShutterList><FilterWheel FluorifierAutoSelection="1" BeamSplitterAutoSelection="1" StedBeamSelectionPinholeCoupling="0" MultiFunctionPortAutoSelection="0" BeamMergerAutoSelectionEnabled="0" RldBlockingFilterAutoSelectionEnabled="0"><Wheel Version="0" Qualifier="40" FilterWheelName="Excitation Beam Splitter" FilterIndex="2" FilterName="DD 488/552" IsSpectrumTurnMode="0" FilterSpectrumPos="0" IndexChanged="0" SpectrumChanged="0"><BeamRoute Version="0"/></Wheel><Wheel Version="0" Qualifier="131" FilterWheelName="Notch FW 2" FilterIndex="0" FilterName="Empty" IsSpectrumTurnMode="0" FilterSpectrumPos="0" IndexChanged="0" SpectrumChanged="0"><BeamRoute Version="0"/></Wheel><Wheel Version="0" Qualifier="130" FilterWheelName="Polarization FW" FilterIndex="3" FilterName="NF 488" IsSpectrumTurnMode="0" FilterSpectrumPos="79196" IndexChanged="0" SpectrumChanged="0"><BeamRoute Version="0"/></Wheel><Wheel Version="0" Qualifier="170" FilterWheelName="Target Slider" FilterIndex="0" FilterName="Target Park " IsSpectrumTurnMode="0" FilterSpectrumPos="0" IndexChanged="0" SpectrumChanged="0"><BeamRoute Version="0"/></Wheel><Wheel Version="0" Qualifier="31" FilterWheelName="X2 Lens Changer" FilterIndex="0" FilterName="CS2 UV Optics 1 " IsSpectrumTurnMode="0" FilterSpectrumPos="0" IndexChanged="0" SpectrumChanged="0"><BeamRoute Version="0"/></Wheel></FilterWheel><Spectro><MultiBand Channel="1" ChannelName="Channel 1" LeftWorld="493" RightWorld="659" TargetWaveLengthBegin="493" TargetWaveLengthEnd="659" DyeName="Leica/EGFP"/><MultiBand Channel="2" ChannelName="Channel 2" LeftWorld="659" RightWorld="789" TargetWaveLengthBegin="659" TargetWaveLengthEnd="789" DyeName=""/><MultiBand Channel="3" ChannelName="Channel 3" LeftWorld="790" RightWorld="795" TargetWaveLengthBegin="790" TargetWaveLengthEnd="795" DyeName=""/><MultiBand Channel="4" ChannelName="Channel 4" LeftWorld="795" RightWorld="800" TargetWaveLengthBegin="795" TargetWaveLengthEnd="800" DyeName=""/></Spectro><AotfList><Aotf Version="0" LightSourceName="UV" LightSourceType="1" OpenVirtual="0" IsChanged="0" CanDoPulseFreq="0" PulsFreq="0" CanDoTwoLaserPIE="0" TwoLaserPIEPossibleLastState="0" TwoLaserPIEActive="0"><BeamRoute Version="0"><BeamPosition BeamPositionLevel="0" BeamPosition="30"/></BeamRoute><LaserLineSetting LaserLine="405" IntensityDev="0" IntensityLowDev="0" AOBSIntensityDev="-1" AOBSIntensityLowDev="-1" EnableDoubleMode="0" LineIndex="0" SequenceIndex="0" LineDeactivationFlags="0" IsLineChecked="1" OutCheckedIntensity="0" SuppressionMode="-1" IsVisible="1" CanDoFastModulation="1"/></Aotf><Aotf Version="0" LightSourceName="Visible" LightSourceType="0" OpenVirtual="0" IsChanged="1" CanDoPulseFreq="0" PulsFreq="0" CanDoTwoLaserPIE="0" TwoLaserPIEPossibleLastState="0" TwoLaserPIEActive="0"><BeamRoute Version="0"><BeamPosition BeamPositionLevel="0" BeamPosition="10"/></BeamRoute><LaserLineSetting LaserLine="488" IntensityDev="49.9952060174489" IntensityLowDev="0" AOBSIntensityDev="-1" AOBSIntensityLowDev="-1" EnableDoubleMode="0" LineIndex="0" SequenceIndex="0" LineDeactivationFlags="0" IsLineChecked="1" OutCheckedIntensity="0" SuppressionMode="-1" IsVisible="1" CanDoFastModulation="1"/><LaserLineSetting LaserLine="552" IntensityDev="0" IntensityLowDev="0" AOBSIntensityDev="-1" AOBSIntensityLowDev="-1" EnableDoubleMode="0" LineIndex="1" SequenceIndex="0" LineDeactivationFlags="0" IsLineChecked="1" OutCheckedIntensity="0" SuppressionMode="-1" IsVisible="1" CanDoFastModulation="1"/><LaserLineSetting LaserLine="638" IntensityDev="0" IntensityLowDev="0" AOBSIntensityDev="-1" AOBSIntensityLowDev="-1" EnableDoubleMode="0" LineIndex="2" SequenceIndex="0" LineDeactivationFlags="0" IsLineChecked="1" OutCheckedIntensity="0" SuppressionMode="-1" IsVisible="1" CanDoFastModulation="1"/></Aotf></AotfList><LUT_List><LUT Channel="1" LutName="Green"/><LUT Channel="2" LutName="Green"/><LUT Channel="3" LutName="Red"/><LUT Channel="4" LutName="Blue"/><LUT Channel="100" LutName="Gray"/></LUT_List><DetectorList DetectorAutoSelection="1" InExternalDetectionMode="0"><Detector Name="PMT 1" Type="PMT" ScanType="Internal" Channel="1" ChannelName="Channel 1" IsActive="1" Gain="732.318608377203" Offset="0" IsSTEDDetector="1" IsSRSDetector="0" DetectionRangeBegin="0" DetectionRangeEnd="0" Phase="0" IsFlimDetector="0" IsHPDDetector="0" CanDoTimeGate="0"/><Detector Name="PMT 2" Type="PMT" ScanType="Internal" Channel="2" ChannelName="Channel 2" IsActive="0" Gain="649.519340810254" Offset="0" IsSTEDDetector="1" IsSRSDetector="0" DetectionRangeBegin="0" DetectionRangeEnd="0" Phase="0" IsFlimDetector="0" IsHPDDetector="0" CanDoTimeGate="0"/><Detector Name="HyD 3" Type="HyD" ScanType="Internal" Channel="3" ChannelName="Channel 3" IsActive="0" Gain="500" Offset="-6.6666666666606E-03" IsSTEDDetector="1" IsSRSDetector="0" DetectionRangeBegin="0" DetectionRangeEnd="0" Phase="0" IsFlimDetector="0" IsHPDDetector="1" IsEnabled="0" IsHPDOverloaded="0" CanDoPhotonCounting="1" AcquisitionMode="0" AcquisitionModeName="PhotonIntegration" CanDoTimeGate="0"/><Detector Name="HyD 4" Type="HyD" ScanType="Internal" Channel="4" ChannelName="Channel 4" IsActive="0" Gain="99.9981315396114" Offset="-6.6666666666606E-03" IsSTEDDetector="1" IsSRSDetector="0" DetectionRangeBegin="0" DetectionRangeEnd="0" Phase="0" IsFlimDetector="0" IsHPDDetector="1" IsEnabled="0" IsHPDOverloaded="0" CanDoPhotonCounting="1" AcquisitionMode="0" AcquisitionModeName="PhotonIntegration" CanDoTimeGate="0"/><Detector Name="PMT Trans" Type="PMT" ScanType="TLD" Channel="100" ChannelName="Transmission Channel" IsActive="1" Gain="190.165560387579" Offset="0" IsSTEDDetector="0" IsSRSDetector="0" DetectionRangeBegin="0" DetectionRangeEnd="0" Phase="0" IsFlimDetector="0" IsHPDDetector="0" CanDoTimeGate="0"/></DetectorList><LaserArray><Laser Version="6" LightSourceType="1" LaserName="Diode 405" PowerState="Off" StedAlignFlag="0" CanDoLinearOutputPower="0" CanDoPulsing="0" CanDoOutputPowerWatt="1" HighPowerModeActive="0" LightSourceName="UV" OutputPowerWatt="0" Wavelength="405" CanDoChangeWavelength="0"><BeamRoute Version="0"><BeamPosition BeamPositionLevel="0" BeamPosition="30"/></BeamRoute></Laser><Laser Version="6" LightSourceType="0" LaserName="Diode 638" PowerState="Off" StedAlignFlag="0" CanDoLinearOutputPower="0" CanDoPulsing="0" CanDoOutputPowerWatt="1" HighPowerModeActive="0" LightSourceName="Visible" OutputPowerWatt="0" Wavelength="638" CanDoChangeWavelength="0"><BeamRoute Version="0"><BeamPosition BeamPositionLevel="0" BeamPosition="10"/></BeamRoute></Laser><Laser Version="6" LightSourceType="0" LaserName="OPSL 488" PowerState="On" StedAlignFlag="0" CanDoLinearOutputPower="0" CanDoPulsing="0" CanDoOutputPowerWatt="1" HighPowerModeActive="0" LightSourceName="Visible" OutputPowerWatt="0" Wavelength="488" CanDoChangeWavelength="0"><BeamRoute Version="0"><BeamPosition BeamPositionLevel="0" BeamPosition="10"/></BeamRoute></Laser><Laser Version="6" LightSourceType="0" LaserName="OPSL 552" PowerState="On" StedAlignFlag="0" CanDoLinearOutputPower="0" CanDoPulsing="0" CanDoOutputPowerWatt="1" HighPowerModeActive="0" LightSourceName="Visible" OutputPowerWatt="0" Wavelength="552" CanDoChangeWavelength="0"><BeamRoute Version="0"><BeamPosition BeamPositionLevel="0" BeamPosition="10"/></BeamRoute></Laser></LaserArray><OnlineDyeSeparation Enabled="0" KeepRawImage="0" Detectors="0" Channels="0" Normalize="0"><OnlineDyeSeparationDetectorList/><OnlineDyeSeparationChannelList/></OnlineDyeSeparation><VariableBeamExpanderFactors CommonSettingEnabled="0" CommonFactor="1.03"/></ATLConfocalSettingDefinition><ATLConfocalSettingDefinition VersionNumber="15" UserSettingName="Seq. 2" CanDoSTED="0" IsSTEDActive="0" IsSwitchForPulsedStedWithMpActive="0" UseSystemOptimizedVoxelCalculation="1" IsUserSettingNameSet="1" IsHydPulsedModeCoeffntManualActive="0" CanDoCSMode="1" ActiveCS_SubModeForTLD="0" ActiveCS_SubModeForTLDName="Scan-BF" RldFluoCubePos="3" RldCubeAutoSelectionEnabled="1" Pinhole="9.62741725510108E-05" PinholeAiry="1.00783213524078" EmissionWavelengthForPinholeAiryCalculation="580" FrameAverage="1" LineAverage="1" FrameAccumulation="1" Line_Accumulation="1" AreBleachPointsEnabled="0" IsRoiScanEnable="0" ZCompensationModes="0" WizardMode="0"><EasySRMappingArray/><EasySRSlider SRRelative="75" ThreeDRelative="0" GentleRelative="25"/><ShutterList><Shutter Version="0" LightSourceType="1" LightSourceName="UV" IsActive="0"><BeamRoute Version="0"><BeamPosition BeamPositionLevel="0" BeamPosition="30"/></BeamRoute></Shutter><Shutter Version="0" LightSourceType="0" LightSourceName="Visible" IsActive="1"><BeamRoute Version="0"><BeamPosition BeamPositionLevel="0" BeamPosition="10"/></BeamRoute></Shutter></ShutterList><FilterWheel FluorifierAutoSelection="1" BeamSplitterAutoSelection="1" StedBeamSelectionPinholeCoupling="0" MultiFunctionPortAutoSelection="0" BeamMergerAutoSelectionEnabled="0" RldBlockingFilterAutoSelectionEnabled="1"><Wheel Version="0" Qualifier="40" FilterWheelName="Excitation Beam Splitter" FilterIndex="2" FilterName="DD 488/552" IsSpectrumTurnMode="0" FilterSpectrumPos="0" IndexChanged="0" SpectrumChanged="0"><BeamRoute Version="0"/></Wheel><Wheel Version="0" Qualifier="131" FilterWheelName="Notch FW 2" FilterIndex="1" FilterName="NF 552" IsSpectrumTurnMode="0" FilterSpectrumPos="0" IndexChanged="0" SpectrumChanged="0"><BeamRoute Version="0"/></Wheel><Wheel Version="0" Qualifier="130" FilterWheelName="Polarization FW" FilterIndex="0" FilterName="Empty" IsSpectrumTurnMode="0" FilterSpectrumPos="79196" IndexChanged="0" SpectrumChanged="0"><BeamRoute Version="0"/></Wheel><Wheel Version="0" Qualifier="170" FilterWheelName="Target Slider" FilterIndex="0" FilterName="Target Park " IsSpectrumTurnMode="0" FilterSpectrumPos="0" IndexChanged="0" SpectrumChanged="0"><BeamRoute Version="0"/></Wheel><Wheel Version="0" Qualifier="31" FilterWheelName="X2 Lens Changer" FilterIndex="0" FilterName="CS2 UV Optics 1 " IsSpectrumTurnMode="0" FilterSpectrumPos="0" IndexChanged="0" SpectrumChanged="0"><BeamRoute Version="0"/></Wheel></FilterWheel><Spectro><MultiBand Channel="1" ChannelName="Channel 1" LeftWorld="493" RightWorld="557" TargetWaveLengthBegin="493" TargetWaveLengthEnd="557" DyeName=""/><MultiBand Channel="2" ChannelName="Channel 2" LeftWorld="557" RightWorld="789" TargetWaveLengthBegin="557" TargetWaveLengthEnd="789" DyeName="Leica/mCherry"/><MultiBand Channel="3" ChannelName="Channel 3" LeftWorld="790" RightWorld="795" TargetWaveLengthBegin="790" TargetWaveLengthEnd="795" DyeName=""/><MultiBand Channel="4" ChannelName="Channel 4" LeftWorld="795" RightWorld="800" TargetWaveLengthBegin="795" TargetWaveLengthEnd="800" DyeName=""/></Spectro><AotfList><Aotf Version="0" LightSourceName="UV" LightSourceType="1" OpenVirtual="0" IsChanged="0" CanDoPulseFreq="0" PulsFreq="0" CanDoTwoLaserPIE="0" TwoLaserPIEPossibleLastState="0" TwoLaserPIEActive="0"><BeamRoute Version="0"><BeamPosition BeamPositionLevel="0" BeamPosition="30"/></BeamRoute><LaserLineSetting LaserLine="405" IntensityDev="0" IntensityLowDev="0" AOBSIntensityDev="-1" AOBSIntensityLowDev="-1" EnableDoubleMode="0" LineIndex="0" SequenceIndex="0" LineDeactivationFlags="0" IsLineChecked="1" OutCheckedIntensity="0" SuppressionMode="-1" IsVisible="1" CanDoFastModulation="1"/></Aotf><Aotf Version="0" LightSourceName="Visible" LightSourceType="0" OpenVirtual="0" IsChanged="1" CanDoPulseFreq="0" PulsFreq="0" CanDoTwoLaserPIE="0" TwoLaserPIEPossibleLastState="0" TwoLaserPIEActive="0"><BeamRoute Version="0"><BeamPosition BeamPositionLevel="0" BeamPosition="10"/></BeamRoute><LaserLineSetting LaserLine="488" IntensityDev="0" IntensityLowDev="0" AOBSIntensityDev="-1" AOBSIntensityLowDev="-1" EnableDoubleMode="0" LineIndex="0" SequenceIndex="0" LineDeactivationFlags="0" IsLineChecked="1" OutCheckedIntensity="0" SuppressionMode="-1" IsVisible="1" CanDoFastModulation="1"/><LaserLineSetting LaserLine="552" IntensityDev="75.000000000006" IntensityLowDev="0" AOBSIntensityDev="-1" AOBSIntensityLowDev="-1" EnableDoubleMode="0" LineIndex="1" SequenceIndex="0" LineDeactivationFlags="0" IsLineChecked="1" OutCheckedIntensity="0" SuppressionMode="-1" IsVisible="1" CanDoFastModulation="1"/><LaserLineSetting LaserLine="638" IntensityDev="0" IntensityLowDev="0" AOBSIntensityDev="-1" AOBSIntensityLowDev="-1" EnableDoubleMode="0" LineIndex="2" SequenceIndex="0" LineDeactivationFlags="0" IsLineChecked="1" OutCheckedIntensity="0" SuppressionMode="-1" IsVisible="1" CanDoFastModulation="1"/></Aotf></AotfList><LUT_List><LUT Channel="1" LutName="Blue"/><LUT Channel="2" LutName="Red"/><LUT Channel="3" LutName="Red"/><LUT Channel="4" LutName="Blue"/><LUT Channel="100" LutName="Gray"/></LUT_List><DetectorList DetectorAutoSelection="1" InExternalDetectionMode="0"><Detector Name="PMT 1" Type="PMT" ScanType="Internal" Channel="1" ChannelName="Channel 1" IsActive="0" Gain="0" Offset="0" IsSTEDDetector="1" IsSRSDetector="0" DetectionRangeBegin="0" DetectionRangeEnd="0" Phase="0" IsFlimDetector="0" IsHPDDetector="0" CanDoTimeGate="0"/><Detector Name="PMT 2" Type="PMT" ScanType="Internal" Channel="2" ChannelName="Channel 2" IsActive="1" Gain="658.350499732967" Offset="0" IsSTEDDetector="1" IsSRSDetector="0" DetectionRangeBegin="0" DetectionRangeEnd="0" Phase="0" IsFlimDetector="0" IsHPDDetector="0" CanDoTimeGate="0"/><Detector Name="HyD 3" Type="HyD" ScanType="Internal" Channel="3" ChannelName="Channel 3" IsActive="0" Gain="500" Offset="-6.6666666666606E-03" IsSTEDDetector="1" IsSRSDetector="0" DetectionRangeBegin="0" DetectionRangeEnd="0" Phase="0" IsFlimDetector="0" IsHPDDetector="1" IsEnabled="0" IsHPDOverloaded="0" CanDoPhotonCounting="1" AcquisitionMode="0" AcquisitionModeName="PhotonIntegration" CanDoTimeGate="0"/><Detector Name="HyD 4" Type="HyD" ScanType="Internal" Channel="4" ChannelName="Channel 4" IsActive="0" Gain="99.9981315396114" Offset="-6.6666666666606E-03" IsSTEDDetector="1" IsSRSDetector="0" DetectionRangeBegin="0" DetectionRangeEnd="0" Phase="0" IsFlimDetector="0" IsHPDDetector="1" IsEnabled="0" IsHPDOverloaded="0" CanDoPhotonCounting="1" AcquisitionMode="0" AcquisitionModeName="PhotonIntegration" CanDoTimeGate="0"/><Detector Name="PMT Trans" Type="PMT" ScanType="TLD" Channel="100" ChannelName="Transmission Channel" IsActive="0" Gain="234.779125658045" Offset="0" IsSTEDDetector="0" IsSRSDetector="0" DetectionRangeBegin="0" DetectionRangeEnd="0" Phase="0" IsFlimDetector="0" IsHPDDetector="0" CanDoTimeGate="0"/></DetectorList><LaserArray><Laser Version="6" LightSourceType="1" LaserName="Diode 405" PowerState="Off" StedAlignFlag="0" CanDoLinearOutputPower="0" CanDoPulsing="0" CanDoOutputPowerWatt="1" HighPowerModeActive="0" LightSourceName="UV" OutputPowerWatt="0" Wavelength="405" CanDoChangeWavelength="0"><BeamRoute Version="0"><BeamPosition BeamPositionLevel="0" BeamPosition="30"/></BeamRoute></Laser><Laser Version="6" LightSourceType="0" LaserName="Diode 638" PowerState="Off" StedAlignFlag="0" CanDoLinearOutputPower="0" CanDoPulsing="0" CanDoOutputPowerWatt="1" HighPowerModeActive="0" LightSourceName="Visible" OutputPowerWatt="0" Wavelength="638" CanDoChangeWavelength="0"><BeamRoute Version="0"><BeamPosition BeamPositionLevel="0" BeamPosition="10"/></BeamRoute></Laser><Laser Version="6" LightSourceType="0" LaserName="OPSL 488" PowerState="On" StedAlignFlag="0" CanDoLinearOutputPower="0" CanDoPulsing="0" CanDoOutputPowerWatt="1" HighPowerModeActive="0" LightSourceName="Visible" OutputPowerWatt="0" Wavelength="488" CanDoChangeWavelength="0"><BeamRoute Version="0"><BeamPosition BeamPositionLevel="0" BeamPosition="10"/></BeamRoute></Laser><Laser Version="6" LightSourceType="0" LaserName="OPSL 552" PowerState="On" StedAlignFlag="0" CanDoLinearOutputPower="0" CanDoPulsing="0" CanDoOutputPowerWatt="1" HighPowerModeActive="0" LightSourceName="Visible" OutputPowerWatt="0" Wavelength="552" CanDoChangeWavelength="0"><BeamRoute Version="0"><BeamPosition BeamPositionLevel="0" BeamPosition="10"/></BeamRoute></Laser></LaserArray><OnlineDyeSeparation Enabled="0" KeepRawImage="0" Detectors="0" Channels="0" Normalize="0"><OnlineDyeSeparationDetectorList/><OnlineDyeSeparationChannelList/></OnlineDyeSeparation><VariableBeamExpanderFactors CommonSettingEnabled="0" CommonFactor="1.03"/></ATLConfocalSettingDefinition></LDM_Block_Sequential_List><LDM_Block_Sequential_Execution_Mask><InstrumentSettingMask Shutter="1" Frame_Average="1" Line_Average="1" AOTF="1" Attenuator_Wheel="1" Laser_Gain_Offset="1" PMTs_on_off="1" PMTs_Gain_Offset="1" Timegate="1" HyDs_Acquistion_Mode="1" HyDs_Pulse_Calibr_Value="1" FilterWheel="1" Variable_Beam_Expander="1" Microscope="1" Pinhole="1" Z_Compensation="1" Spectrophotometer="1" Mot_Corr_Ring="0" Frame_Accumulation="1" Line_Accumulation="1" Laser="1" STED_DelayTime="1"/></LDM_Block_Sequential_Execution_Mask></LDM_Block_Sequential></Attachment></Image></Data>
